ieeefp/__init__.py
ieeefp/ieeefp.py
ieeefp-0.1.2.dist-info/METADATA
ieeefp-0.1.2.dist-info/WHEEL
ieeefp-0.1.2.dist-info/entry_points.txt
ieeefp-0.1.2.dist-info/top_level.txt
ieeefp-0.1.2.dist-info/RECORD
